fastapi_async_langchain/__init__.py
fastapi_async_langchain/callbacks/__init__.py
fastapi_async_langchain/callbacks/base.py
fastapi_async_langchain/callbacks/llm.py
fastapi_async_langchain/callbacks/qa_with_sources.py
fastapi_async_langchain/callbacks/retrieval_qa.py
fastapi_async_langchain/register.py
fastapi_async_langchain/responses/__init__.py
fastapi_async_langchain/responses/streaming.py
fastapi_async_langchain/schemas.py
fastapi_async_langchain/testing/__init__.py
fastapi_async_langchain/testing/gradio.py
fastapi_async_langchain/testing/settings.py
fastapi_async_langchain/websockets/__init__.py
fastapi_async_langchain/websockets/base.py
fastapi_async_langchain-0.5.5.dist-info/LICENSE
fastapi_async_langchain-0.5.5.dist-info/METADATA
fastapi_async_langchain-0.5.5.dist-info/WHEEL
fastapi_async_langchain-0.5.5.dist-info/RECORD
