Metadata-Version: 2.1
Name: fastapi-async-langchain
Version: 0.5.5
Summary: Ship production-ready LangChain projects with FastAPI
Home-page: https://github.com/ajndkr/fastapi-async-langchain
License: MIT
Author: Ajinkya Indulkar
Author-email: 26824103+ajndkr@users.noreply.github.com
Requires-Python: >=3.9,<4.0
Classifier: License :: OSI Approved :: MIT License
Classifier: Programming Language :: Python :: 3
Classifier: Programming Language :: Python :: 3.9
Classifier: Programming Language :: Python :: 3.10
Classifier: Programming Language :: Python :: 3.11
Requires-Dist: fastapi (>=0.95.1,<0.96.0)
Requires-Dist: langchain (>=0.0.167)
Requires-Dist: python-dotenv (>=1.0.0,<2.0.0)
Requires-Dist: urllib3 (<=1.26.15)
Project-URL: Repository, https://github.com/ajndkr/fastapi-async-langchain
